{
  "id": "your-module-id",
  "title": "Your Module Title",
  "description": "A brief description of what your module does.",
  "version": "0.1.0",
  "authors": [
    {
      "name": "Your Name",
      "discord": "",
      "flags": {}
    }
  ],
  "compatibility": {
    "minimum": "13",
    "verified": "13"
  },
  "relationships": {
    "requires": [],
    "recommends": []
  },
  "esmodules": [
    "scripts/main.js",
    "scripts/shared.js",
    "scripts/settings.js"
  ],
  "styles": [
    "styles/styles.css"
  ],
  "license": "MIT",
  "url": "https://github.com/yourusername/your-module-id",
  "readme": "https://github.com/yourusername/your-module-id/blob/main/README.md",
  "manifest": "https://github.com/yourusername/your-module-id/releases/latest/download/module.json",
  "download": "https://github.com/yourusername/your-module-id/releases/latest/download/your-module-id.zip"
}
